{
  "libraryId": "constraintlayout",
  "groupId": "androidx.constraintlayout",
  "version": "2.0.4",
  "releaseDate": "2020-10-29",
  "changelogHtml": "<h3 id=\"constraintlayout-2.0.4\" data-text=\"Version 2.0.4\" tabindex=\"-1\">Version 2.0.4</h3>\n<p>October 29, 2020</p>\n<p><code translate=\"no\" dir=\"ltr\">androidx.constraintlayout:constraintlayout:2.0.4</code> is released.</p>\n<p><strong>Bug Fixes</strong></p>\n<p>This releases fixes a potential NPE that may happen when removing a child view\nat runtime. It is recommended to update to this version.</p>\n<p>See the list of closed issues <a href=\"https://androidstudio.googleblog.com/2020/10/constraintlayout-204.html\">here</a>.</p>"
}