{
  "libraryId": "constraintlayout",
  "groupId": "androidx.constraintlayout",
  "version": "2.1.0-beta01",
  "releaseDate": "2021-03-11",
  "changelogHtml": "<h3 id=\"constraintlayout-2.1.0-beta01\" data-text=\"Version 2.1.0-beta01\" tabindex=\"-1\">Version 2.1.0-beta01</h3>\n<p>March 11, 2021</p>\n<p><code translate=\"no\" dir=\"ltr\">androidx.constraintlayout:constraintlayout:2.1.0-beta01</code> is released.</p>\n<p><strong>ConstraintLayout</strong></p>\n<p>android:layout_width and android:layout_height are back being non-optional due to compatibility issues.</p>\n<p><strong>MotionLayout</strong></p>\n<ul>\n<li>Programmatic support for inserting and removing onSwipe and onClick on Transitions</li>\n<li>Experimental Support for Transitions through screen rotation</li>\n<li>support duration argument to transitions</li>\n<li>Better support for customAttributes that are boolean or References</li>\n</ul>\n<p><strong>Helpers</strong></p>\n<ul>\n<li>added a way to animate or jump directly to a given item of a Carousel</li>\n<li>new CircularFlow helper</li>\n</ul>\n<p>See additional information on this release\n<a href=\"https://github.com/androidx/constraintlayout/wiki/What's-New-in-2.1\">here</a>\nand <a href=\"https://androidstudio.googleblog.com/2021/03/constraintlayout-210-beta-1.html\">bugs closed</a>.</p>"
}